pymmWave/IWR6843AOP.py
pymmWave/__init__.py
pymmWave/algos.py
pymmWave/constants.py
pymmWave/data_model.py
pymmWave/logging.py
pymmWave/sensor.py
pymmWave/utils.py
pymmWave/__pycache__/IWR6843AOP.cpython-39.pyc
pymmWave/__pycache__/__init__.cpython-39.pyc
pymmWave/__pycache__/algos.cpython-39.pyc
pymmWave/__pycache__/constants.cpython-39.pyc
pymmWave/__pycache__/data_model.cpython-39.pyc
pymmWave/__pycache__/logging.cpython-39.pyc
pymmWave/__pycache__/sensor.cpython-39.pyc
pymmWave/__pycache__/utils.cpython-39.pyc
pymmWave/mmWave/IWR6843AOP.pyi
pymmWave/mmWave/constants.pyi
pymmWave/mmWave/data_model.pyi
pymmWave/mmWave/sensor.pyi
pymmWave/mmWave/utils.pyi
pymmWave-1.1.2.dist-info/LICENSE
pymmWave-1.1.2.dist-info/METADATA
pymmWave-1.1.2.dist-info/WHEEL
pymmWave-1.1.2.dist-info/top_level.txt
pymmWave-1.1.2.dist-info/RECORD
