Metadata-Version: 2.1
Name: pymmWave
Version: 1.1.2
Summary: A TI mmWave RADAR EVM integration library.
Home-page: https://pymmwave.readthedocs.io/en/latest/#
Author-email: peterfeghali@ucsb.edu
License: UNKNOWN
Platform: UNKNOWN
Requires-Python: >3.9
